{
    "url":  "https://rgsneddon.github.io/evolve/downloads/v4.0.0/evolve-v4.0.0-android-setup.apk",
    "build":  "136",
    "platform":  "android",
    "version":  "4.0.0",
    "sizeMb":  74.8,
    "sha512":  "86782c863fd3e6f4d8dfb0ef3cc95b79d3d14b6901c33e4aae026f18234eba0ba3672d261f240ff3c8efbbf51e87d72cdda3832fc2a78f39774239c8870677be",
    "name":  "evolve-v4.0.0-android-setup.apk",
    "minSdk":  23,
    "sha256":  "aab63909e5ebaaad5efe2b7195c6103cdbabceb91137e3700aa98563c0f1e996",
    "abis":  [
                 "arm64-v8a",
                 "armeabi-v7a",
                 "x86_64"
             ],
    "sizeBytes":  78403713
}
