{
  "transferTxId": "tx-3",
  "transferBlockIndex": 1,
  "ledger": {
    "version": 9,
    "evolutionaryChainId": "evolve-chronoflux-principia-chain-1",
    "chronofluxPrincipiaId": "chronoflux-principia-roy-d-herbert",
    "mainChainId": "perc-main-evolve-1",
    "sideChainId": "perc-chronoflux-side-1",
    "connectedAppVersion": "4.1.5+169",
    "evolvedAppVersions": [],
    "evolutionSteps": [],
    "evolutionEpoch": 1,
    "networkGenesisRevision": 2,
    "accounts": {
      "evolve_treasury": {
        "username": "evolve_treasury",
        "passwordHash": "a35a578b332be3e24d8dd68cb67fa22ab3f9ceb40a46fd70ff2a825e33adc272",
        "salt": "nnsqFd1_q6YYmitepy3saQ==",
        "address": "percpriv1ce8c6aae1d6d11a3a988cdd6f054867cf5ba7768",
        "passwordSet": true,
        "balance": {
          "microUnits": 20000000
        },
        "cumulativeStakingEarned": {
          "microUnits": 0
        },
        "transactions": [
          {
            "id": "tx-2",
            "kind": "scenarioReward",
            "amount": {
              "microUnits": 80000000
            },
            "timestamp": "2026-07-13T21:02:11.765087Z",
            "fromUsername": "evolve_treasury",
            "toUsername": "android_user",
            "scenarioLabel": "Scenario analysis reward",
            "percentChance": 80.0,
            "blockIndex": 0,
            "confirmations": 1
          },
          {
            "id": "tx-1",
            "kind": "treasuryEmission",
            "amount": {
              "microUnits": 100000000
            },
            "timestamp": "2026-07-13T21:02:11.765087Z",
            "toUsername": "evolve_treasury",
            "blockIndex": 0,
            "confirmations": 1
          }
        ]
      },
      "android_user": {
        "username": "android_user",
        "passwordHash": "13461c723ca384147d1caf60974f1673e862a383d7088e0da1dd1985a34522b0",
        "salt": "nW44R9jJH7Ld3H1qi0WU1g==",
        "address": "percpriv16d6ad6a0131579ccb754f49da842077702305b93",
        "passwordSet": true,
        "balance": {
          "microUnits": 80000000
        },
        "lastFaucetDrawAt": "2026-07-13T21:02:11.765087Z",
        "cumulativeStakingEarned": {
          "microUnits": 0
        },
        "scenarioBlockHeight": 1,
        "passwordSwitchCommit": "swc1b0e6fee8139920f0ce2065ab65a019b7",
        "transactions": [
          {
            "id": "tx-3",
            "kind": "transfer",
            "amount": {
              "microUnits": 5
            },
            "timestamp": "2026-07-13T21:02:11.782094Z",
            "fromUsername": "android_user",
            "toUsername": "windows_user",
            "blockIndex": 1
          },
          {
            "id": "tx-2",
            "kind": "scenarioReward",
            "amount": {
              "microUnits": 80000000
            },
            "timestamp": "2026-07-13T21:02:11.765087Z",
            "fromUsername": "evolve_treasury",
            "toUsername": "android_user",
            "scenarioLabel": "Scenario analysis reward",
            "percentChance": 80.0,
            "blockIndex": 0,
            "confirmations": 1
          }
        ]
      },
      "windows_user": {
        "username": "windows_user",
        "passwordHash": "",
        "salt": "",
        "address": "percpriv1882fb3ffdd00ae360144d7359f68bf0b91680d8d",
        "passwordSet": false,
        "balance": {
          "microUnits": 0
        },
        "cumulativeStakingEarned": {
          "microUnits": 0
        },
        "transactions": [
          {
            "id": "tx-3",
            "kind": "transfer",
            "amount": {
              "microUnits": 5
            },
            "timestamp": "2026-07-13T21:02:11.782094Z",
            "fromUsername": "android_user",
            "toUsername": "windows_user",
            "blockIndex": 1
          }
        ]
      }
    },
    "blocks": [
      {
        "index": 0,
        "timestamp": "2026-07-13T21:02:11.765087Z",
        "transactions": [
          {
            "id": "tx-1",
            "kind": "treasuryEmission",
            "amount": {
              "microUnits": 100000000
            },
            "timestamp": "2026-07-13T21:02:11.765087Z",
            "toUsername": "evolve_treasury",
            "blockIndex": 0,
            "confirmations": 1
          },
          {
            "id": "tx-2",
            "kind": "scenarioReward",
            "amount": {
              "microUnits": 80000000
            },
            "timestamp": "2026-07-13T21:02:11.765087Z",
            "fromUsername": "evolve_treasury",
            "toUsername": "android_user",
            "scenarioLabel": "Scenario analysis reward",
            "percentChance": 80.0,
            "blockIndex": 0,
            "confirmations": 1
          }
        ],
        "treasuryEmitted": {
          "microUnits": 100000000
        },
        "triggerUsername": "android_user"
      },
      {
        "index": 1,
        "timestamp": "2026-07-13T21:02:11.782094Z",
        "transactions": [
          {
            "id": "tx-3",
            "kind": "transfer",
            "amount": {
              "microUnits": 5
            },
            "timestamp": "2026-07-13T21:02:11.782094Z",
            "fromUsername": "android_user",
            "toUsername": "windows_user",
            "blockIndex": 1
          }
        ],
        "treasuryEmitted": {
          "microUnits": 0
        },
        "triggerUsername": "android_user"
      }
    ],
    "lastScenarioAt": "2026-07-13T21:02:11.765087Z",
    "treasuryGenesisDone": true,
    "cumulativeTreasuryMinted": {
      "microUnits": 100000000
    },
    "cumulativeBurnedPerc": {
      "microUnits": 0
    },
    "treasuryCycle": 1,
    "blockchainLaunched": true,
    "sessionUsername": "android_user",
    "sessionStartedAt": "2026-07-13T21:02:11.779091Z",
    "sessionLastActivityAt": "2026-07-13T21:02:11.779091Z",
    "nextTxId": 4,
    "microblockCount": 0,
    "totalMicroblocks": 0,
    "walletPeers": {
      "android_user": [
        "evolve_treasury",
        "windows_user"
      ],
      "evolve_treasury": [
        "android_user",
        "windows_user"
      ],
      "windows_user": [
        "android_user",
        "evolve_treasury"
      ]
    },
    "networkNodes": {
      "evolve_seed_node": {
        "username": "evolve_seed_node",
        "blockHeight": 0,
        "tipHash": "d5f6c62ecae7c98c94fc657435b407a8cbb5f37e42fd4b1379a14f3d49fe8049",
        "online": false,
        "lastSeen": "2026-07-13T21:02:11.762090Z"
      },
      "evolve_treasury": {
        "username": "evolve_treasury",
        "blockHeight": 0,
        "tipHash": "d5f6c62ecae7c98c94fc657435b407a8cbb5f37e42fd4b1379a14f3d49fe8049",
        "online": false,
        "lastSeen": "2026-07-13T21:02:11.762090Z"
      },
      "android_user": {
        "username": "android_user",
        "blockHeight": 0,
        "tipHash": "d5f6c62ecae7c98c94fc657435b407a8cbb5f37e42fd4b1379a14f3d49fe8049",
        "online": false,
        "lastSeen": "2026-07-13T21:02:11.762090Z"
      },
      "windows_user": {
        "username": "windows_user",
        "blockHeight": 0,
        "tipHash": "d5f6c62ecae7c98c94fc657435b407a8cbb5f37e42fd4b1379a14f3d49fe8049",
        "online": false,
        "lastSeen": "2026-07-13T21:02:11.762090Z"
      }
    },
    "wardProposals": [],
    "wardBallots": [],
    "nextWardProposalId": 1,
    "pendingInboundTransfers": [
      {
        "id": "tx-3",
        "fromUsername": "android_user",
        "toUsername": "windows_user",
        "toAddress": "percpriv1882fb3ffdd00ae360144d7359f68bf0b91680d8d",
        "amount": {
          "microUnits": 5
        },
        "fee": {
          "microUnits": 1
        },
        "sentAt": "2026-07-13T21:02:11.782094Z",
        "recipientBroughtOnlineAt": "2026-07-13T21:02:11.782094Z",
        "switchCommitment": "swc123624cf96c378b3373c6031152067f93"
      }
    ],
    "settlementWitnesses": [],
    "microblockLog": []
  }
}